{
    "src_folder": ["bundled/e2e-test"],
    "output_folder": "reports",
    "selenium": {
        "start_process": false
    },
    "test_setting": {
        "default": {
            "silent": true,
            "screenshots": {
                "enabled": true,
                "path": "screenshots"
            },
            "desiredCapabilities": {
                "browserName": "chrome",
                "javascriptEnable": true,
                "acceptSslCerts": true
            }
        },
        "phantomjs": {
            "desiredCapabilities": {
                "browserName": "phantomjs",
                "javascriptEnable": true,
                "acceptSslCerts": true,
                "phantomjs.binary.path": "./node_modules/phantomjs/bin/phantomjs"
            }
        },
        "chrome": {
            "desiredCapabilities": {
                "browserName": "chrome",
                "javascriptEnable": true,
                "acceptSslCerts": true
            }
        }
    }
}
